LICENSE.md
README.md
setup.cfg
setup.py
Topsis_Aadil_102017047.egg-info/PKG-INFO
Topsis_Aadil_102017047.egg-info/SOURCES.txt
Topsis_Aadil_102017047.egg-info/dependency_links.txt
Topsis_Aadil_102017047.egg-info/entry_points.txt
Topsis_Aadil_102017047.egg-info/requires.txt
Topsis_Aadil_102017047.egg-info/top_level.txt
topsis/__init__.py
topsis/__main__.py