Metadata-Version: 2.1
Name: Topsis-Aadil-102017047
Version: 0.0.1
Summary: Useful in solving MCDM problems
Author: Aadil Singh
Author-email: aadilsandhu7@gmail.com
License: MIT
Classifier: License :: OSI Approved :: MIT License
Classifier: Programming Language :: Python :: 3.8
Classifier: Programming Language :: Python :: 3.9
Classifier: Programming Language :: Python :: 3.10
License-File: LICENSE.md
